s2geometry/s2PYTHON_wrap.cxx
s2geometry/_pywraps2.so
s2geometry/pywraps2.py
s2geometry/__init__.py
s2geometry/.libs/libz-eb09ad1d.so.1.2.3
s2geometry-0.9.0.dist-info/NOTICE
s2geometry-0.9.0.dist-info/RECORD
s2geometry-0.9.0.dist-info/LICENSE
s2geometry-0.9.0.dist-info/WHEEL
s2geometry-0.9.0.dist-info/top_level.txt
s2geometry-0.9.0.dist-info/METADATA
